Metadata-Version: 1.1
Name: simple-ml
Version: 0.1.1
Summary: Machine learning tool simplified for hackers
Home-page: https://github.com/luanjunyi/simple-ml
Author: Jerry Luan
Author-email: luanjunyi@gmail.com
License: MIT
Platform: UNKNOWN
Classifier: Development Status :: 3 - Alpha
Classifier: License :: OSI Approved :: MIT License
Classifier: Programming Language :: Python :: 2.7
Classifier: Topic :: Scientific/Engineering :: Artificial Intelligence
